setup.py
distributions_sergi/Binomialdistribution.py
distributions_sergi/Gaussiandistribution.py
distributions_sergi/Generaldistribution.py
distributions_sergi/__init__.py
distributions_sergi.egg-info/PKG-INFO
distributions_sergi.egg-info/SOURCES.txt
distributions_sergi.egg-info/dependency_links.txt
distributions_sergi.egg-info/not-zip-safe
distributions_sergi.egg-info/top_level.txt